funniest_321/__init__.py
funniest_321-0.1.dist-info/METADATA
funniest_321-0.1.dist-info/RECORD
funniest_321-0.1.dist-info/WHEEL
funniest_321-0.1.dist-info/top_level.txt
