Metadata-Version: 2.1
Name: funniest-321
Version: 0.1
Summary: The funniest joke in the world
Home-page: http://github.com/ruknight/funniest_321
Author: ruknight
Author-email: manyacservice@gmail.com
License: MIT
Platform: UNKNOWN
